{
  "version-0.7.4/someSidebar": [
    {
      "collapsed": true,
      "type": "category",
      "label": "项目简介",
      "items": [
        {
          "type": "doc",
          "id": "version-0.7.4/00-0-Docs"
        }
      ]
    },
    {
      "collapsed": true,
      "type": "category",
      "label": "快速入门",
      "items": [
        {
          "type": "doc",
          "id": "version-0.7.4/01-0-Quick-Start"
        },
        {
          "type": "doc",
          "id": "version-0.7.4/01-1-Create-Project"
        },
        {
          "type": "doc",
          "id": "version-0.7.4/01-2-Simple-Event-Flow"
        },
        {
          "type": "doc",
          "id": "version-0.7.4/01-3-New-Claptrap"
        },
        {
          "type": "doc",
          "id": "version-0.7.4/01-4-Start-With-Minion"
        }
      ]
    },
    {
      "collapsed": true,
      "type": "category",
      "label": "术语表",
      "items": [
        {
          "type": "doc",
          "id": "version-0.7.4/02-0-Glossary"
        },
        {
          "type": "doc",
          "id": "version-0.7.4/02-1-Actor-Pattern"
        },
        {
          "type": "doc",
          "id": "version-0.7.4/02-10-Claptrap-Identity"
        },
        {
          "type": "doc",
          "id": "version-0.7.4/02-11-Claptrap-Box"
        },
        {
          "type": "doc",
          "id": "version-0.7.4/02-12-Claptrap-Lifetime-Scope"
        },
        {
          "type": "doc",
          "id": "version-0.7.4/02-13-Serialization"
        },
        {
          "type": "doc",
          "id": "version-0.7.4/02-14-Minimal-Competing-Resources"
        },
        {
          "type": "doc",
          "id": "version-0.7.4/02-2-Event-Sourcing"
        },
        {
          "type": "doc",
          "id": "version-0.7.4/02-3-Claptrap"
        },
        {
          "type": "doc",
          "id": "version-0.7.4/02-4-Minion"
        },
        {
          "type": "doc",
          "id": "version-0.7.4/02-5-Event"
        },
        {
          "type": "doc",
          "id": "version-0.7.4/02-6-State"
        },
        {
          "type": "doc",
          "id": "version-0.7.4/02-7-State-Snapshot"
        },
        {
          "type": "doc",
          "id": "version-0.7.4/02-8-Claptrap-Design"
        },
        {
          "type": "doc",
          "id": "version-0.7.4/02-9-Claptrap-Factory"
        }
      ]
    },
    {
      "collapsed": true,
      "type": "category",
      "label": "项目样例-火车售票",
      "items": [
        {
          "type": "doc",
          "id": "version-0.7.4/03-0-Newbe-Claptrap-Ticketing"
        },
        {
          "type": "doc",
          "id": "version-0.7.4/03-1-Design"
        },
        {
          "type": "doc",
          "id": "version-0.7.4/03-2-Impletmentation"
        },
        {
          "type": "doc",
          "id": "version-0.7.4/03-3-Deployment"
        }
      ]
    }
  ]
}
